cli_tool_test/__init__.py
cli_tool_test/__main__.py
cli_tool_test/prog.py
cli_tool_test-0.0.4.dist-info/METADATA
cli_tool_test-0.0.4.dist-info/WHEEL
cli_tool_test-0.0.4.dist-info/entry_points.txt
cli_tool_test-0.0.4.dist-info/top_level.txt
cli_tool_test-0.0.4.dist-info/zip-safe
cli_tool_test-0.0.4.dist-info/RECORD
