Metadata-Version: 2.1
Name: cli-tool-test
Version: 0.0.4
Summary: Sample CLI tool in python
Home-page: UNKNOWN
Author: UNKNOWN
Author-email: UNKNOWN
License: UNKNOWN
Platform: UNKNOWN
Requires-Dist: Click
Requires-Dist: pyfiglet
